tabicl/__about__.py
tabicl/__init__.py
tabicl/model/__init__.py
tabicl/model/attention.py
tabicl/model/embedding.py
tabicl/model/encoders.py
tabicl/model/inference.py
tabicl/model/inference_config.py
tabicl/model/interaction.py
tabicl/model/layers.py
tabicl/model/learning.py
tabicl/model/rope.py
tabicl/model/tabicl.py
tabicl/prior/__init__.py
tabicl/prior/activations.py
tabicl/prior/dataset.py
tabicl/prior/genload.py
tabicl/prior/hp_sampling.py
tabicl/prior/mlp_scm.py
tabicl/prior/prior_config.py
tabicl/prior/reg2cls.py
tabicl/prior/tree_scm.py
tabicl/prior/utils.py
tabicl/sklearn/__init__.py
tabicl/sklearn/classifier.py
tabicl/sklearn/preprocessing.py
tabicl/train/__init__.py
tabicl/train/optim.py
tabicl/train/run.py
tabicl/train/train_config.py
tabicl-0.1.3.dist-info/METADATA
tabicl-0.1.3.dist-info/WHEEL
tabicl-0.1.3.dist-info/licenses/LICENSE
tabicl-0.1.3.dist-info/RECORD
