Metadata-Version: 2.4
Name: tabicl
Version: 0.1.3
Summary: TabICL: A Tabular Foundation Model for In-Context Learning on Large Data
Project-URL: Documentation, https://github.com/soda-inria/tabicl#readme
Project-URL: Issues, https://github.com/soda-inria/tabicl/issues
Project-URL: Source, https://github.com/soda-inria/tabicl
Author: Jingang Qu, David Holzmüller, Marine Le Morvan, Gaël Varoquaux
License: BSD 3-Clause License
License-File: LICENSE
Keywords: TabICL,foundation model,in-context learning,tabular data
Classifier: Development Status :: 4 - Beta
Classifier: Intended Audience :: Developers
Classifier: Intended Audience :: Science/Research
Classifier: Programming Language :: Python
Classifier: Programming Language :: Python :: 3
Classifier: Programming Language :: Python :: 3.9
Classifier: Programming Language :: Python :: 3.10
Classifier: Programming Language :: Python :: 3.11
Classifier: Programming Language :: Python :: 3.12
Classifier: Topic :: Scientific/Engineering
Requires-Python: <3.13,>=3.9
Requires-Dist: einops>=0.7
Requires-Dist: huggingface-hub
Requires-Dist: joblib
Requires-Dist: numpy
Requires-Dist: psutil
Requires-Dist: scikit-learn<1.7,>=1.3.0
Requires-Dist: scipy
Requires-Dist: torch<3,>=2.2
Requires-Dist: tqdm>=4.64.0
Requires-Dist: transformers
Requires-Dist: wandb
Requires-Dist: xgboost
